mandeintegration/__init__.py
mandeintegration/command.py
mandeintegration/config/__init__.py
mandeintegration/config/selectors.py
mandeintegration/config/types.py
mandeintegration/config/variables.py
mandeintegration/data.py
mandeintegration/organizations.py
mandeintegration/utils/__init__.py
mandeintegration-0.1.8.dist-info/WHEEL
mandeintegration-0.1.8.dist-info/METADATA
mandeintegration-0.1.8.dist-info/RECORD
