Metadata-Version: 2.1
Name: mandeintegration
Version: 0.1.8
Summary: Mande Integration package
Author: Sylvain Kadjo
Author-email: sylvain.kadjo@sejen.ci
Requires-Python: >=3.10,<4.0
Classifier: Programming Language :: Python :: 3
Classifier: Programming Language :: Python :: 3.10
Requires-Dist: beautifulsoup4 (>=4.11.1,<5.0.0)
Requires-Dist: python-slugify (>=6.1.2,<7.0.0)
Requires-Dist: selenium (>=4.2.0,<5.0.0)
Requires-Dist: webdriver-manager (>=3.7.0,<4.0.0)
